{
  "version": 3,
  "middleware": {
    "/": {
      "files": [
        "server/edge-runtime-webpack.js",
        "server/src/middleware.js"
      ],
      "name": "src/middleware",
      "page": "/",
      "matchers": [
        {
          "regexp": "^(?:\\/(_next\\/data\\/[^/]{1,}))?\\/dashboard(?:\\/((?:[^\\/#\\?]+?)(?:\\/(?:[^\\/#\\?]+?))*))?(\\.json|\\.rsc|\\.segments\\/.+\\.segment\\.rsc)?[\\/#\\?]?$",
          "originalSource": "/dashboard/:path*"
        },
        {
          "regexp": "^(?:\\/(_next\\/data\\/[^/]{1,}))?\\/admin(?:\\/((?:[^\\/#\\?]+?)(?:\\/(?:[^\\/#\\?]+?))*))?(\\.json|\\.rsc|\\.segments\\/.+\\.segment\\.rsc)?[\\/#\\?]?$",
          "originalSource": "/admin/:path*"
        },
        {
          "regexp": "^(?:\\/(_next\\/data\\/[^/]{1,}))?\\/owner(?:\\/((?:[^\\/#\\?]+?)(?:\\/(?:[^\\/#\\?]+?))*))?(\\.json|\\.rsc|\\.segments\\/.+\\.segment\\.rsc)?[\\/#\\?]?$",
          "originalSource": "/owner/:path*"
        }
      ],
      "wasm": [],
      "assets": [],
      "env": {
        "__NEXT_BUILD_ID": "p8JDazOsbtvFU0nhfrYjc",
        "NEXT_SERVER_ACTIONS_ENCRYPTION_KEY": "RN86teV4wJsNj8F3+eqjlGa55y2qOHJXHLh9fsKZit0=",
        "__NEXT_PREVIEW_MODE_ID": "63bb5272e93caa8ddf21c2f5b96f839a",
        "__NEXT_PREVIEW_MODE_SIGNING_KEY": "027f8e8185bbb8ddd2e460c2de97b15081845bb0653e7a7e1b7c67f5548476c4",
        "__NEXT_PREVIEW_MODE_ENCRYPTION_KEY": "ffefb561d6dc47d02eb5ffe3ce6ab41e3689a585d4ec7450270a53f61217478e"
      }
    }
  },
  "functions": {},
  "sortedMiddleware": [
    "/"
  ]
}